external_arrow/register_cpp_arrow.py
external_arrow/__init__.py
external_arrow/lib/cpp_arrow/test_object_detector.so
external_arrow/arrow/test_object_detector.py
external_arrow/arrow/__init__.py
external_arrow-0.0.2.dist-info/RECORD
external_arrow-0.0.2.dist-info/WHEEL
external_arrow-0.0.2.dist-info/LICENSE
external_arrow-0.0.2.dist-info/top_level.txt
external_arrow-0.0.2.dist-info/METADATA
external_arrow-0.0.2.dist-info/entry_points.txt
