Metadata-Version: 2.1
Name: external-arrow
Version: 0.0.2
Summary: UNKNOWN
Home-page: UNKNOWN
License: UNKNOWN
Platform: linux
Platform: Unix
Classifier: Development Status :: 3 - Alpha
Classifier: Intended Audience :: Developers
Classifier: Programming Language :: Python :: 3.5
Classifier: Programming Language :: Python :: 3.6
Classifier: Programming Language :: Python :: 3.7
Classifier: Programming Language :: Python :: 3.8
Classifier: Operating System :: Unix
Classifier: License :: OSI Approved :: BSD License
Requires-Python: >=3.5
Requires-Dist: kwiver (>=1.4.2)
Requires-Dist: diva-framework (>=0.0.3)
